{
  "type": "FeatureCollection",
  "features": [
    {
      "type": "Feature",
      "properties": {
        "zoom": 14,
        "title": "cool places",
        "address": "",
        "postalCode": "",
        "city": "",
        "state": "",
        "country": "",
        "phone": "",
        "email": "",
        "website": "",
        "tag": "",
        "class_icon": "",
        "class_marker": "",
        "class_markerColor": "",
        "class_iconColor": "",
        "class_Extra": ""
      },
      "geometry": {
        "type": "Point",
        "coordinates": [
          2.3500,
          48.8528
        ]
      }
    }
  ]
}
