{
  "type": "FeatureCollection",
  "features": [
    {
      "type": "Feature",
      "properties": {
        "zoom": 14,
        "title": "MoZilla France",
        "address": "16bis Boulevard Montmartre",
        "postalCode": "75009",
        "city": "Paris",
        "state": "",
        "country": "",
        "phone": "",
        "email": "",
        "website": "https://twitter.com/MozillaParis",
        "tag": "meetups",
        "class_icon": "",
        "class_marker": "",
        "class_markerColor": "",
        "class_iconColor": "",
        "class_Extra": ""
      },
      "geometry": {
        "type": "Point",
        "coordinates": [
          2.3412305116653442,
          48.871969704539794
        ]
      }
    }
  ]
}
